{
  "wordCount": 1557,
  "words": [
    {
      "line": 67,
      "count": 1,
      "position": 474,
      "word": "shabazz"
    },
    {
      "line": 40,
      "count": 2,
      "position": 285,
      "word": "half"
    },
    {
      "line": 47,
      "count": 1,
      "position": 329,
      "word": "bad"
    },
    {
      "line": 7,
      "count": 8,
      "position": 52,
      "word": "don't"
    },
    {
      "line": 31,
      "count": 1,
      "position": 220,
      "word": "dippity-hippity"
    },
    {
      "line": 73,
      "count": 2,
      "position": 514,
      "word": "hall"
    },
    {
      "line": 201,
      "count": 1,
      "position": 1410,
      "word": "boys"
    },
    {
      "line": 26,
      "count": 1,
      "position": 185,
      "word": "clinton"
    },
    {
      "line": 1,
      "count": 4,
      "position": 11,
      "word": "your"
    },
    {
      "line": 48,
      "count": 2,
      "position": 339,
      "word": "yeah"
    },
    {
      "line": 21,
      "count": 1,
      "position": 153,
      "word": "laptop"
    },
    {
      "line": 18,
      "count": 1,
      "position": 131,
      "word": "robot"
    },
    {
      "line": 36,
      "count": 4,
      "position": 256,
      "word": "these"
    },
    {
      "line": 199,
      "count": 2,
      "position": 1394,
      "word": "satan"
    },
    {
      "line": 40,
      "count": 1,
      "position": 282,
      "word": "crack"
    },
    {
      "line": 198,
      "count": 1,
      "position": 1392,
      "word": "drunk"
    },
    {
      "line": 63,
      "count": 3,
      "position": 445,
      "word": "music"
    },
    {
      "line": 218,
      "count": 1,
      "position": 1527,
      "word": "trip"
    },
    {
      "line": 28,
      "count": 1,
      "position": 202,
      "word": "honest"
    },
    {
      "line": 59,
      "count": 1,
      "position": 414,
      "word": "exuberance"
    },
    {
      "line": 68,
      "count": 1,
      "position": 477,
      "word": "cube"
    },
    {
      "line": 58,
      "count": 1,
      "position": 409,
      "word": "blueprint's"
    },
    {
      "line": 1,
      "count": 35,
      "position": 7,
      "word": "you"
    },
    {
      "line": 13,
      "count": 13,
      "position": 96,
      "word": "rap"
    },
    {
      "line": 7,
      "count": 1,
      "position": 49,
      "word": "happen"
    },
    {
      "line": 34,
      "count": 1,
      "position": 242,
      "word": "ac"
    },
    {
      "line": 169,
      "count": 1,
      "position": 1183,
      "word": "audience"
    },
    {
      "line": 70,
      "count": 1,
      "position": 493,
      "word": "grow"
    },
    {
      "line": 121,
      "count": 1,
      "position": 847,
      "word": "sure"
    },
    {
      "line": 2,
      "count": 1,
      "position": 16,
      "word": "going"
    },
    {
      "line": 180,
      "count": 1,
      "position": 1262,
      "word": "shock"
    },
    {
      "line": 176,
      "count": 1,
      "position": 1232,
      "word": "mainstream"
    },
    {
      "line": 26,
      "count": 1,
      "position": 184,
      "word": "bill"
    },
    {
      "line": 121,
      "count": 1,
      "position": 852,
      "word": "scratch"
    },
    {
      "line": 69,
      "count": 1,
      "position": 488,
      "word": "inspired"
    },
    {
      "line": 150,
      "count": 3,
      "position": 1052,
      "word": "ray"
    },
    {
      "line": 213,
      "count": 1,
      "position": 1496,
      "word": "am"
    },
    {
      "line": 0,
      "count": 1,
      "position": 5,
      "word": "easy"
    },
    {
      "line": 28,
      "count": 4,
      "position": 198,
      "word": "an"
    },
    {
      "line": 10,
      "count": 11,
      "position": 72,
      "word": "as"
    },
    {
      "line": 35,
      "count": 7,
      "position": 249,
      "word": "at"
    },
    {
      "line": 67,
      "count": 1,
      "position": 472,
      "word": "rakim"
    },
    {
      "line": 134,
      "count": 1,
      "position": 942,
      "word": "trying"
    },
    {
      "line": 82,
      "count": 11,
      "position": 578,
      "word": "looking"
    },
    {
      "line": 207,
      "count": 1,
      "position": 1453,
      "word": "consideration"
    },
    {
      "line": 6,
      "count": 1,
      "position": 43,
      "word": "i've"
    },
    {
      "line": 1,
      "count": 1,
      "position": 10,
      "word": "hurt"
    },
    {
      "line": 80,
      "count": 1,
      "position": 565,
      "word": "plank"
    },
    {
      "line": 20,
      "count": 15,
      "position": 146,
      "word": "be"
    },
    {
      "line": 189,
      "count": 1,
      "position": 1323,
      "word": "prove"
    },
    {
      "line": 73,
      "count": 1,
      "position": 513,
      "word": "roll"
    },
    {
      "line": 119,
      "count": 1,
      "position": 838,
      "word": "least"
    },
    {
      "line": 178,
      "count": 1,
      "position": 1248,
      "word": "hop"
    },
    {
      "line": 111,
      "count": 1,
      "position": 778,
      "word": "dead"
    },
    {
      "line": 109,
      "count": 1,
      "position": 763,
      "word": "immediately"
    },
    {
      "line": 111,
      "count": 1,
      "position": 783,
      "word": "talking"
    },
    {
      "line": 42,
      "count": 5,
      "position": 299,
      "word": "how"
    },
    {
      "line": 126,
      "count": 2,
      "position": 886,
      "word": "hungry"
    },
    {
      "line": 140,
      "count": 1,
      "position": 985,
      "word": "see"
    },
    {
      "line": 36,
      "count": 2,
      "position": 252,
      "word": "same"
    },
    {
      "line": 108,
      "count": 1,
      "position": 757,
      "word": "omnipotent"
    },
    {
      "line": 19,
      "count": 1,
      "position": 135,
      "word": "rap-bot"
    },
    {
      "line": 112,
      "count": 1,
      "position": 786,
      "word": "zombie"
    },
    {
      "line": 211,
      "count": 1,
      "position": 1480,
      "word": "handing"
    },
    {
      "line": 138,
      "count": 1,
      "position": 970,
      "word": "columbine"
    },
    {
      "line": 42,
      "count": 1,
      "position": 296,
      "word": "after"
    },
    {
      "line": 125,
      "count": 1,
      "position": 876,
      "word": "punchlines"
    },
    {
      "line": 194,
      "count": 1,
      "position": 1359,
      "word": "bully"
    },
    {
      "line": 133,
      "count": 1,
      "position": 933,
      "word": "mine"
    },
    {
      "line": 5,
      "count": 59,
      "position": 41,
      "word": "a"
    },
    {
      "line": 12,
      "count": 1,
      "position": 88,
      "word": "ordered"
    },
    {
      "line": 195,
      "count": 1,
      "position": 1370,
      "word": "mind"
    },
    {
      "line": 127,
      "count": 1,
      "position": 892,
      "word": "lunchtime"
    },
    {
      "line": 201,
      "count": 1,
      "position": 1407,
      "word": "d"
    },
    {
      "line": 97,
      "count": 1,
      "position": 682,
      "word": "keeping"
    },
    {
      "line": 44,
      "count": 1,
      "position": 309,
      "word": "f"
    },
    {
      "line": 184,
      "count": 1,
      "position": 1288,
      "word": "words"
    },
    {
      "line": 0,
      "count": 55,
      "position": 1,
      "word": "i"
    },
    {
      "line": 152,
      "count": 2,
      "position": 1068,
      "word": "j"
    },
    {
      "line": 161,
      "count": 1,
      "position": 1130,
      "word": "dooma"
    },
    {
      "line": 12,
      "count": 53,
      "position": 86,
      "word": "the"
    },
    {
      "line": 157,
      "count": 1,
      "position": 1105,
      "word": "straight"
    },
    {
      "line": 3,
      "count": 2,
      "position": 26,
      "word": "something's"
    },
    {
      "line": 71,
      "count": 1,
      "position": 503,
      "word": "meet"
    },
    {
      "line": 105,
      "count": 1,
      "position": 741,
      "word": "krypton"
    },
    {
      "line": 180,
      "count": 1,
      "position": 1266,
      "word": "throw"
    },
    {
      "line": 69,
      "count": 1,
      "position": 483,
      "word": "thank"
    },
    {
      "line": 13,
      "count": 8,
      "position": 97,
      "word": "god"
    },
    {
      "line": 17,
      "count": 4,
      "position": 121,
      "word": "slap"
    },
    {
      "line": 61,
      "count": 1,
      "position": 429,
      "word": "did"
    },
    {
      "line": 48,
      "count": 1,
      "position": 338,
      "word": "masterpiece"
    },
    {
      "line": 140,
      "count": 1,
      "position": 984,
      "word": "nine"
    },
    {
      "line": 39,
      "count": 1,
      "position": 278,
      "word": "couple"
    },
    {
      "line": 164,
      "count": 1,
      "position": 1148,
      "word": "superhuman"
    },
    {
      "line": 47,
      "count": 1,
      "position": 332,
      "word": "wack"
    },
    {
      "line": 131,
      "count": 1,
      "position": 923,
      "word": "sometimes"
    },
    {
      "line": 68,
      "count": 1,
      "position": 476,
      "word": "n-w-a"
    },
    {
      "line": 43,
      "count": 5,
      "position": 306,
      "word": "do"
    },
    {
      "line": 6,
      "count": 6,
      "position": 44,
      "word": "got"
    },
    {
      "line": 119,
      "count": 1,
      "position": 836,
      "word": "good"
    },
    {
      "line": 27,
      "count": 1,
      "position": 192,
      "word": "lewinski"
    },
    {
      "line": 48,
      "count": 8,
      "position": 341,
      "word": "'cause"
    },
    {
      "line": 154,
      "count": 1,
      "position": 1080,
      "word": "pad"
    },
    {
      "line": 164,
      "count": 1,
      "position": 1154,
      "word": "rubber"
    },
    {
      "line": 68,
      "count": 1,
      "position": 480,
      "word": "ren"
    },
    {
      "line": 210,
      "count": 1,
      "position": 1475,
      "word": "discrimination"
    },
    {
      "line": 173,
      "count": 1,
      "position": 1211,
      "word": "celebrating"
    },
    {
      "line": 139,
      "count": 1,
      "position": 977,
      "word": "add"
    },
    {
      "line": 188,
      "count": 1,
      "position": 1321,
      "word": "murder"
    },
    {
      "line": 89,
      "count": 1,
      "position": 624,
      "word": "pat"
    },
    {
      "line": 216,
      "count": 1,
      "position": 1518,
      "word": "need"
    },
    {
      "line": 116,
      "count": 1,
      "position": 815,
      "word": "pay"
    },
    {
      "line": 30,
      "count": 1,
      "position": 212,
      "word": "syllables"
    },
    {
      "line": 86,
      "count": 5,
      "position": 604,
      "word": "take"
    },
    {
      "line": 94,
      "count": 3,
      "position": 663,
      "word": "never"
    },
    {
      "line": 214,
      "count": 1,
      "position": 1498,
      "word": "supposed"
    },
    {
      "line": 75,
      "count": 1,
      "position": 525,
      "word": "burst"
    },
    {
      "line": 82,
      "count": 2,
      "position": 576,
      "word": "little"
    },
    {
      "line": 123,
      "count": 2,
      "position": 865,
      "word": "some"
    },
    {
      "line": 113,
      "count": 1,
      "position": 793,
      "word": "deep"
    },
    {
      "line": 5,
      "count": 1,
      "position": 37,
      "word": "shady"
    },
    {
      "line": 13,
      "count": 3,
      "position": 91,
      "word": "beginning"
    },
    {
      "line": 171,
      "count": 1,
      "position": 1198,
      "word": "waiting"
    },
    {
      "line": 19,
      "count": 10,
      "position": 138,
      "word": "for"
    },
    {
      "line": 15,
      "count": 11,
      "position": 108,
      "word": "back"
    },
    {
      "line": 97,
      "count": 1,
      "position": 680,
      "word": "capable"
    },
    {
      "line": 191,
      "count": 1,
      "position": 1338,
      "word": "unghh"
    },
    {
      "line": 33,
      "count": 1,
      "position": 234,
      "word": "packing"
    },
    {
      "line": 85,
      "count": 1,
      "position": 599,
      "word": "watching"
    },
    {
      "line": 22,
      "count": 1,
      "position": 159,
      "word": "pen'll"
    },
    {
      "line": 33,
      "count": 1,
      "position": 236,
      "word": "mack"
    },
    {
      "line": 216,
      "count": 1,
      "position": 1512,
      "word": "fatal"
    },
    {
      "line": 5,
      "count": 6,
      "position": 38,
      "word": "you're"
    },
    {
      "line": 59,
      "count": 1,
      "position": 418,
      "word": "root"
    },
    {
      "line": 9,
      "count": 2,
      "position": 65,
      "word": "trouble"
    },
    {
      "line": 165,
      "count": 1,
      "position": 1161,
      "word": "ricochet"
    },
    {
      "line": 55,
      "count": 2,
      "position": 386,
      "word": "hard"
    },
    {
      "line": 5,
      "count": 6,
      "position": 40,
      "word": "just"
    },
    {
      "line": 159,
      "count": 1,
      "position": 1118,
      "word": "lyrics"
    },
    {
      "line": 162,
      "count": 1,
      "position": 1136,
      "word": "human"
    },
    {
      "line": 39,
      "count": 1,
      "position": 273,
      "word": "over"
    },
    {
      "line": 215,
      "count": 2,
      "position": 1506,
      "word": "mistake"
    },
    {
      "line": 3,
      "count": 4,
      "position": 22,
      "word": "six"
    },
    {
      "line": 25,
      "count": 1,
      "position": 176,
      "word": "living"
    },
    {
      "line": 37,
      "count": 1,
      "position": 262,
      "word": "practicing"
    },
    {
      "line": 0,
      "count": 3,
      "position": 4,
      "word": "go"
    },
    {
      "line": 41,
      "count": 1,
      "position": 287,
      "word": "realized"
    },
    {
      "line": 64,
      "count": 1,
      "position": 454,
      "word": "'bus"
    },
    {
      "line": 90,
      "count": 1,
      "position": 635,
      "word": "label"
    },
    {
      "line": 186,
      "count": 1,
      "position": 1308,
      "word": "versus"
    },
    {
      "line": 35,
      "count": 1,
      "position": 245,
      "word": "crap"
    },
    {
      "line": 156,
      "count": 1,
      "position": 1096,
      "word": "special"
    },
    {
      "line": 27,
      "count": 13,
      "position": 190,
      "word": "with"
    },
    {
      "line": 68,
      "count": 1,
      "position": 482,
      "word": "eazy"
    },
    {
      "line": 203,
      "count": 1,
      "position": 1424,
      "word": "tugging"
    },
    {
      "line": 127,
      "count": 1,
      "position": 895,
      "word": "there"
    },
    {
      "line": 93,
      "count": 2,
      "position": 657,
      "word": "i'mma"
    },
    {
      "line": 57,
      "count": 2,
      "position": 404,
      "word": "well"
    },
    {
      "line": 45,
      "count": 2,
      "position": 316,
      "word": "rappers"
    },
    {
      "line": 10,
      "count": 3,
      "position": 70,
      "word": "he"
    },
    {
      "line": 11,
      "count": 1,
      "position": 79,
      "word": "taking"
    },
    {
      "line": 22,
      "count": 1,
      "position": 157,
      "word": "pocket"
    },
    {
      "line": 9,
      "count": 3,
      "position": 66,
      "word": "big"
    },
    {
      "line": 158,
      "count": 1,
      "position": 1110,
      "word": "very"
    },
    {
      "line": 190,
      "count": 1,
      "position": 1336,
      "word": "virgins"
    },
    {
      "line": 143,
      "count": 1,
      "position": 1006,
      "word": "immortal"
    },
    {
      "line": 5,
      "count": 2,
      "position": 36,
      "word": "slim"
    },
    {
      "line": 157,
      "count": 1,
      "position": 1100,
      "word": "channel"
    },
    {
      "line": 185,
      "count": 1,
      "position": 1296,
      "word": "occurs"
    },
    {
      "line": 36,
      "count": 1,
      "position": 255,
      "word": "attempt"
    },
    {
      "line": 191,
      "count": 1,
      "position": 1341,
      "word": "pill"
    },
    {
      "line": 137,
      "count": 1,
      "position": 962,
      "word": "tried"
    },
    {
      "line": 145,
      "count": 1,
      "position": 1020,
      "word": "four"
    },
    {
      "line": 107,
      "count": 1,
      "position": 755,
      "word": "rodent"
    },
    {
      "line": 187,
      "count": 1,
      "position": 1313,
      "word": "inadvertently"
    },
    {
      "line": 206,
      "count": 1,
      "position": 1447,
      "word": "hate"
    },
    {
      "line": 35,
      "count": 1,
      "position": 246,
      "word": "yap-yap"
    },
    {
      "line": 144,
      "count": 1,
      "position": 1010,
      "word": "portal"
    },
    {
      "line": 7,
      "count": 8,
      "position": 55,
      "word": "if"
    },
    {
      "line": 148,
      "count": 1,
      "position": 1041,
      "word": "write"
    },
    {
      "line": 202,
      "count": 1,
      "position": 1419,
      "word": "there's"
    },
    {
      "line": 46,
      "count": 1,
      "position": 322,
      "word": "period"
    },
    {
      "line": 157,
      "count": 1,
      "position": 1104,
      "word": "went"
    },
    {
      "line": 9,
      "count": 22,
      "position": 64,
      "word": "in"
    },
    {
      "line": 140,
      "count": 1,
      "position": 981,
      "word": "revolver"
    },
    {
      "line": 24,
      "count": 3,
      "position": 174,
      "word": "made"
    },
    {
      "line": 61,
      "count": 2,
      "position": 430,
      "word": "nothing"
    },
    {
      "line": 210,
      "count": 1,
      "position": 1473,
      "word": "understand"
    },
    {
      "line": 41,
      "count": 1,
      "position": 293,
      "word": "signed"
    },
    {
      "line": 10,
      "count": 4,
      "position": 71,
      "word": "is"
    },
    {
      "line": 4,
      "count": 15,
      "position": 31,
      "word": "it"
    },
    {
      "line": 71,
      "count": 2,
      "position": 498,
      "word": "being"
    },
    {
      "line": 32,
      "count": 2,
      "position": 225,
      "word": "wanna"
    },
    {
      "line": 124,
      "count": 1,
      "position": 868,
      "word": "tough"
    },
    {
      "line": 179,
      "count": 1,
      "position": 1255,
      "word": "hella"
    },
    {
      "line": 200,
      "count": 1,
      "position": 1406,
      "word": "heavy"
    },
    {
      "line": 26,
      "count": 2,
      "position": 182,
      "word": "ever"
    },
    {
      "line": 196,
      "count": 1,
      "position": 1375,
      "word": "million"
    },
    {
      "line": 73,
      "count": 2,
      "position": 517,
      "word": "even"
    },
    {
      "line": 129,
      "count": 1,
      "position": 906,
      "word": "underground"
    },
    {
      "line": 148,
      "count": 1,
      "position": 1039,
      "word": "cornrows"
    },
    {
      "line": 68,
      "count": 2,
      "position": 479,
      "word": "doc"
    },
    {
      "line": 38,
      "count": 3,
      "position": 271,
      "word": "motherfuckin'"
    },
    {
      "line": 116,
      "count": 1,
      "position": 816,
      "word": "homage"
    },
    {
      "line": 160,
      "count": 1,
      "position": 1123,
      "word": "supersonic"
    },
    {
      "line": 206,
      "count": 2,
      "position": 1446,
      "word": "women"
    },
    {
      "line": 160,
      "count": 1,
      "position": 1125,
      "word": "jj"
    },
    {
      "line": 150,
      "count": 1,
      "position": 1053,
      "word": "gun"
    },
    {
      "line": 81,
      "count": 6,
      "position": 572,
      "word": "fuck"
    },
    {
      "line": 132,
      "count": 1,
      "position": 930,
      "word": "skin"
    },
    {
      "line": 114,
      "count": 1,
      "position": 799,
      "word": "noodle"
    },
    {
      "line": 201,
      "count": 1,
      "position": 1412,
      "word": "chunky"
    },
    {
      "line": 82,
      "count": 1,
      "position": 575,
      "word": "thinking"
    },
    {
      "line": 104,
      "count": 1,
      "position": 729,
      "word": "trailer"
    },
    {
      "line": 152,
      "count": 1,
      "position": 1069,
      "word": "mad"
    },
    {
      "line": 94,
      "count": 1,
      "position": 664,
      "word": "asked"
    },
    {
      "line": 133,
      "count": 2,
      "position": 936,
      "word": "too"
    },
    {
      "line": 32,
      "count": 1,
      "position": 229,
      "word": "pissing"
    },
    {
      "line": 57,
      "count": 3,
      "position": 402,
      "word": "have"
    },
    {
      "line": 217,
      "count": 1,
      "position": 1525,
      "word": "vacation"
    },
    {
      "line": 197,
      "count": 1,
      "position": 1382,
      "word": "speak"
    },
    {
      "line": 154,
      "count": 3,
      "position": 1084,
      "word": "man"
    },
    {
      "line": 94,
      "count": 1,
      "position": 660,
      "word": "everything"
    },
    {
      "line": 212,
      "count": 1,
      "position": 1489,
      "word": "can't"
    },
    {
      "line": 38,
      "count": 1,
      "position": 272,
      "word": "table"
    },
    {
      "line": 67,
      "count": 1,
      "position": 470,
      "word": "product"
    },
    {
      "line": 117,
      "count": 1,
      "position": 825,
      "word": "honestly"
    },
    {
      "line": 208,
      "count": 1,
      "position": 1461,
      "word": "may"
    },
    {
      "line": 38,
      "count": 1,
      "position": 269,
      "word": "break"
    },
    {
      "line": 0,
      "count": 2,
      "position": 3,
      "word": "gonna"
    },
    {
      "line": 42,
      "count": 2,
      "position": 300,
      "word": "could"
    },
    {
      "line": 149,
      "count": 1,
      "position": 1049,
      "word": "bought"
    },
    {
      "line": 59,
      "count": 1,
      "position": 416,
      "word": "loves"
    },
    {
      "line": 92,
      "count": 1,
      "position": 644,
      "word": "d'you"
    },
    {
      "line": 23,
      "count": 6,
      "position": 161,
      "word": "off"
    },
    {
      "line": 40,
      "count": 1,
      "position": 280,
      "word": "faggots"
    },
    {
      "line": 122,
      "count": 1,
      "position": 854,
      "word": "scribble"
    },
    {
      "line": 28,
      "count": 1,
      "position": 196,
      "word": "nutsack"
    },
    {
      "line": 62,
      "count": 1,
      "position": 438,
      "word": "mc's"
    },
    {
      "line": 150,
      "count": 1,
      "position": 1056,
      "word": "future"
    },
    {
      "line": 38,
      "count": 1,
      "position": 267,
      "word": "able"
    },
    {
      "line": 73,
      "count": 1,
      "position": 512,
      "word": "n'"
    },
    {
      "line": 54,
      "count": 2,
      "position": 384,
      "word": "ain't"
    },
    {
      "line": 145,
      "count": 1,
      "position": 1019,
      "word": "thousand"
    },
    {
      "line": 122,
      "count": 2,
      "position": 858,
      "word": "rhymes"
    },
    {
      "line": 136,
      "count": 1,
      "position": 958,
      "word": "lp"
    },
    {
      "line": 64,
      "count": 2,
      "position": 448,
      "word": "use"
    },
    {
      "line": 4,
      "count": 6,
      "position": 30,
      "word": "feel"
    },
    {
      "line": 107,
      "count": 1,
      "position": 753,
      "word": "odin"
    },
    {
      "line": 174,
      "count": 1,
      "position": 1223,
      "word": "elevating"
    },
    {
      "line": 27,
      "count": 1,
      "position": 189,
      "word": "office"
    },
    {
      "line": 37,
      "count": 5,
      "position": 260,
      "word": "while"
    },
    {
      "line": 158,
      "count": 1,
      "position": 1107,
      "word": "radio"
    },
    {
      "line": 8,
      "count": 16,
      "position": 56,
      "word": "that"
    },
    {
      "line": 28,
      "count": 1,
      "position": 199,
      "word": "mc"
    },
    {
      "line": 93,
      "count": 1,
      "position": 654,
      "word": "dre"
    },
    {
      "line": 167,
      "count": 1,
      "position": 1175,
      "word": "than"
    },
    {
      "line": 19,
      "count": 15,
      "position": 134,
      "word": "me"
    },
    {
      "line": 157,
      "count": 1,
      "position": 1099,
      "word": "cable"
    },
    {
      "line": 105,
      "count": 1,
      "position": 735,
      "word": "kneel"
    },
    {
      "line": 132,
      "count": 1,
      "position": 926,
      "word": "combine"
    },
    {
      "line": 14,
      "count": 9,
      "position": 100,
      "word": "all"
    },
    {
      "line": 65,
      "count": 2,
      "position": 461,
      "word": "new"
    },
    {
      "line": 48,
      "count": 1,
      "position": 336,
      "word": "constructing"
    },
    {
      "line": 174,
      "count": 1,
      "position": 1220,
      "word": "motivated"
    },
    {
      "line": 29,
      "count": 1,
      "position": 208,
      "word": "indecent"
    },
    {
      "line": 6,
      "count": 3,
      "position": 42,
      "word": "feeling"
    },
    {
      "line": 14,
      "count": 13,
      "position": 101,
      "word": "my"
    },
    {
      "line": 54,
      "count": 1,
      "position": 381,
      "word": "maintaining"
    },
    {
      "line": 104,
      "count": 1,
      "position": 733,
      "word": "trash"
    },
    {
      "line": 11,
      "count": 2,
      "position": 83,
      "word": "were"
    },
    {
      "line": 9,
      "count": 1,
      "position": 63,
      "word": "we're"
    },
    {
      "line": 16,
      "count": 2,
      "position": 116,
      "word": "arms"
    },
    {
      "line": 123,
      "count": 1,
      "position": 861,
      "word": "try"
    },
    {
      "line": 167,
      "count": 1,
      "position": 1173,
      "word": "devastating"
    },
    {
      "line": 71,
      "count": 1,
      "position": 501,
      "word": "position"
    },
    {
      "line": 192,
      "count": 1,
      "position": 1347,
      "word": "accolades"
    },
    {
      "line": 26,
      "count": 2,
      "position": 183,
      "word": "since"
    },
    {
      "line": 57,
      "count": 1,
      "position": 399,
      "word": "immortality"
    },
    {
      "line": 78,
      "count": 1,
      "position": 548,
      "word": "shame"
    },
    {
      "line": 106,
      "count": 1,
      "position": 742,
      "word": "no"
    },
    {
      "line": 121,
      "count": 1,
      "position": 851,
      "word": "chicken"
    },
    {
      "line": 108,
      "count": 1,
      "position": 762,
      "word": "reloading"
    },
    {
      "line": 17,
      "count": 4,
      "position": 122,
      "word": "box"
    },
    {
      "line": 76,
      "count": 1,
      "position": 537,
      "word": "inducted"
    },
    {
      "line": 82,
      "count": 11,
      "position": 579,
      "word": "boy"
    },
    {
      "line": 102,
      "count": 1,
      "position": 718,
      "word": "around"
    },
    {
      "line": 112,
      "count": 2,
      "position": 784,
      "word": "head"
    },
    {
      "line": 75,
      "count": 1,
      "position": 528,
      "word": "ball"
    },
    {
      "line": 124,
      "count": 1,
      "position": 869,
      "word": "times"
    },
    {
      "line": 9,
      "count": 36,
      "position": 68,
      "word": "and"
    },
    {
      "line": 65,
      "count": 1,
      "position": 456,
      "word": "rhyme'"
    },
    {
      "line": 34,
      "count": 20,
      "position": 240,
      "word": "of"
    },
    {
      "line": 155,
      "count": 2,
      "position": 1090,
      "word": "oh"
    },
    {
      "line": 84,
      "count": 1,
      "position": 589,
      "word": "'straight'"
    },
    {
      "line": 120,
      "count": 8,
      "position": 846,
      "word": "make"
    },
    {
      "line": 204,
      "count": 1,
      "position": 1428,
      "word": "fight"
    },
    {
      "line": 0,
      "count": 10,
      "position": 6,
      "word": "on"
    },
    {
      "line": 3,
      "count": 1,
      "position": 21,
      "word": "chance"
    },
    {
      "line": 115,
      "count": 1,
      "position": 805,
      "word": "poodle"
    },
    {
      "line": 153,
      "count": 1,
      "position": 1074,
      "word": "looked"
    },
    {
      "line": 199,
      "count": 1,
      "position": 1398,
      "word": "wheel"
    },
    {
      "line": 86,
      "count": 1,
      "position": 608,
      "word": "oy"
    },
    {
      "line": 11,
      "count": 2,
      "position": 80,
      "word": "any"
    },
    {
      "line": 122,
      "count": 1,
      "position": 856,
      "word": "doodle"
    },
    {
      "line": 211,
      "count": 1,
      "position": 1482,
      "word": "lemons"
    },
    {
      "line": 46,
      "count": 1,
      "position": 328,
      "word": "disastrously"
    },
    {
      "line": 12,
      "count": 1,
      "position": 87,
      "word": "doctor"
    },
    {
      "line": 130,
      "count": 1,
      "position": 915,
      "word": "pharoahe"
    },
    {
      "line": 34,
      "count": 1,
      "position": 243,
      "word": "backpack"
    },
    {
      "line": 60,
      "count": 1,
      "position": 424,
      "word": "earth"
    },
    {
      "line": 214,
      "count": 1,
      "position": 1500,
      "word": "bake"
    },
    {
      "line": 126,
      "count": 1,
      "position": 883,
      "word": "unsigned"
    },
    {
      "line": 58,
      "count": 1,
      "position": 407,
      "word": "truthful"
    },
    {
      "line": 78,
      "count": 1,
      "position": 546,
      "word": "wall"
    },
    {
      "line": 74,
      "count": 2,
      "position": 520,
      "word": "walk"
    },
    {
      "line": 143,
      "count": 2,
      "position": 1007,
      "word": "coming"
    },
    {
      "line": 166,
      "count": 1,
      "position": 1168,
      "word": "glue"
    },
    {
      "line": 84,
      "count": 1,
      "position": 594,
      "word": "witnessing"
    },
    {
      "line": 6,
      "count": 1,
      "position": 47,
      "word": "about"
    },
    {
      "line": 85,
      "count": 1,
      "position": 596,
      "word": "mass-occur"
    },
    {
      "line": 33,
      "count": 1,
      "position": 233,
      "word": "rappity-rap"
    },
    {
      "line": 148,
      "count": 2,
      "position": 1038,
      "word": "fucking"
    },
    {
      "line": 72,
      "count": 1,
      "position": 506,
      "word": "induct"
    },
    {
      "line": 121,
      "count": 1,
      "position": 848,
      "word": "somewhere"
    },
    {
      "line": 143,
      "count": 1,
      "position": 1003,
      "word": "morphin'"
    },
    {
      "line": 192,
      "count": 1,
      "position": 1349,
      "word": "skills"
    },
    {
      "line": 197,
      "count": 1,
      "position": 1384,
      "word": "tongues"
    },
    {
      "line": 214,
      "count": 1,
      "position": 1503,
      "word": "cake"
    },
    {
      "line": 196,
      "count": 1,
      "position": 1377,
      "word": "above"
    },
    {
      "line": 185,
      "count": 1,
      "position": 1301,
      "word": "ripping"
    },
    {
      "line": 53,
      "count": 3,
      "position": 377,
      "word": "let"
    },
    {
      "line": 16,
      "count": 2,
      "position": 114,
      "word": "thinks"
    },
    {
      "line": 17,
      "count": 9,
      "position": 125,
      "word": "they"
    },
    {
      "line": 46,
      "count": 2,
      "position": 323,
      "word": "here's"
    },
    {
      "line": 77,
      "count": 1,
      "position": 541,
      "word": "alcohol"
    },
    {
      "line": 21,
      "count": 1,
      "position": 149,
      "word": "genes"
    },
    {
      "line": 124,
      "count": 3,
      "position": 872,
      "word": "gotta"
    },
    {
      "line": 55,
      "count": 2,
      "position": 391,
      "word": "want"
    },
    {
      "line": 98,
      "count": 1,
      "position": 687,
      "word": "pace"
    },
    {
      "line": 193,
      "count": 2,
      "position": 1354,
      "word": "myself"
    },
    {
      "line": 72,
      "count": 2,
      "position": 507,
      "word": "them"
    },
    {
      "line": 108,
      "count": 4,
      "position": 760,
      "word": "then"
    },
    {
      "line": 202,
      "count": 1,
      "position": 1420,
      "word": "something"
    },
    {
      "line": 42,
      "count": 1,
      "position": 295,
      "word": "aftermath"
    },
    {
      "line": 200,
      "count": 1,
      "position": 1404,
      "word": "seat"
    },
    {
      "line": 29,
      "count": 1,
      "position": 205,
      "word": "rude"
    },
    {
      "line": 20,
      "count": 1,
      "position": 145,
      "word": "must"
    },
    {
      "line": 42,
      "count": 1,
      "position": 298,
      "word": "fact"
    },
    {
      "line": 113,
      "count": 1,
      "position": 794,
      "word": "throating"
    },
    {
      "line": 41,
      "count": 1,
      "position": 290,
      "word": "ironic"
    },
    {
      "line": 122,
      "count": 1,
      "position": 860,
      "word": "maybe"
    },
    {
      "line": 130,
      "count": 1,
      "position": 916,
      "word": "monch"
    },
    {
      "line": 187,
      "count": 1,
      "position": 1311,
      "word": "curtains"
    },
    {
      "line": 25,
      "count": 1,
      "position": 179,
      "word": "killing"
    },
    {
      "line": 66,
      "count": 1,
      "position": 465,
      "word": "students"
    },
    {
      "line": 10,
      "count": 1,
      "position": 73,
      "word": "bananas"
    },
    {
      "line": 206,
      "count": 1,
      "position": 1442,
      "word": "eliminate"
    },
    {
      "line": 145,
      "count": 1,
      "position": 1018,
      "word": "two"
    },
    {
      "line": 16,
      "count": 2,
      "position": 118,
      "word": "long"
    },
    {
      "line": 31,
      "count": 1,
      "position": 219,
      "word": "flippity"
    },
    {
      "line": 172,
      "count": 1,
      "position": 1207,
      "word": "fell"
    },
    {
      "line": 178,
      "count": 1,
      "position": 1250,
      "word": "pop"
    },
    {
      "line": 32,
      "count": 4,
      "position": 227,
      "word": "into"
    },
    {
      "line": 179,
      "count": 1,
      "position": 1253,
      "word": "found"
    },
    {
      "line": 16,
      "count": 6,
      "position": 117,
      "word": "are"
    },
    {
      "line": 45,
      "count": 1,
      "position": 315,
      "word": "attack"
    },
    {
      "line": 62,
      "count": 1,
      "position": 440,
      "word": "taken"
    },
    {
      "line": 128,
      "count": 1,
      "position": 899,
      "word": "where"
    },
    {
      "line": 18,
      "count": 8,
      "position": 132,
      "word": "so"
    },
    {
      "line": 116,
      "count": 1,
      "position": 813,
      "word": "arm"
    },
    {
      "line": 168,
      "count": 1,
      "position": 1177,
      "word": "demonstrating"
    },
    {
      "line": 56,
      "count": 1,
      "position": 393,
      "word": "key"
    },
    {
      "line": 210,
      "count": 1,
      "position": 1471,
      "word": "situation"
    },
    {
      "line": 138,
      "count": 1,
      "position": 968,
      "word": "kids"
    },
    {
      "line": 220,
      "count": 1,
      "position": 1541,
      "word": "retard"
    },
    {
      "line": 8,
      "count": 4,
      "position": 60,
      "word": "think"
    },
    {
      "line": 87,
      "count": 1,
      "position": 611,
      "word": "boy's"
    },
    {
      "line": 147,
      "count": 1,
      "position": 1034,
      "word": "pointless"
    },
    {
      "line": 74,
      "count": 3,
      "position": 518,
      "word": "though"
    },
    {
      "line": 154,
      "count": 1,
      "position": 1081,
      "word": "singin'"
    },
    {
      "line": 2,
      "count": 5,
      "position": 20,
      "word": "one"
    },
    {
      "line": 132,
      "count": 1,
      "position": 927,
      "word": "appeal"
    },
    {
      "line": 188,
      "count": 1,
      "position": 1317,
      "word": "many"
    },
    {
      "line": 14,
      "count": 4,
      "position": 102,
      "word": "people"
    },
    {
      "line": 37,
      "count": 1,
      "position": 259,
      "word": "stunts"
    },
    {
      "line": 19,
      "count": 2,
      "position": 133,
      "word": "call"
    },
    {
      "line": 46,
      "count": 1,
      "position": 327,
      "word": "actually"
    },
    {
      "line": 84,
      "count": 3,
      "position": 590,
      "word": "face"
    },
    {
      "line": 169,
      "count": 1,
      "position": 1188,
      "word": "levitating"
    },
    {
      "line": 54,
      "count": 2,
      "position": 383,
      "word": "shit"
    },
    {
      "line": 1,
      "count": 46,
      "position": 9,
      "word": "to"
    },
    {
      "line": 30,
      "count": 1,
      "position": 213,
      "word": "skill-a-holic"
    },
    {
      "line": 1,
      "count": 1,
      "position": 12,
      "word": "feelings"
    },
    {
      "line": 152,
      "count": 1,
      "position": 1065,
      "word": "fabulous"
    },
    {
      "line": 115,
      "count": 1,
      "position": 808,
      "word": "doberman"
    },
    {
      "line": 1,
      "count": 20,
      "position": 13,
      "word": "but"
    },
    {
      "line": 123,
      "count": 3,
      "position": 867,
      "word": "through"
    },
    {
      "line": 138,
      "count": 1,
      "position": 967,
      "word": "seven"
    },
    {
      "line": 208,
      "count": 1,
      "position": 1458,
      "word": "had"
    },
    {
      "line": 68,
      "count": 1,
      "position": 481,
      "word": "yella"
    },
    {
      "line": 139,
      "count": 1,
      "position": 979,
      "word": "ak-47"
    },
    {
      "line": 161,
      "count": 1,
      "position": 1127,
      "word": "uh"
    },
    {
      "line": 104,
      "count": 1,
      "position": 732,
      "word": "white"
    },
    {
      "line": 63,
      "count": 3,
      "position": 442,
      "word": "school"
    },
    {
      "line": 96,
      "count": 1,
      "position": 674,
      "word": "basically"
    },
    {
      "line": 103,
      "count": 1,
      "position": 725,
      "word": "dale"
    },
    {
      "line": 187,
      "count": 1,
      "position": 1314,
      "word": "hurtin'"
    },
    {
      "line": 61,
      "count": 2,
      "position": 432,
      "word": "shoot"
    },
    {
      "line": 115,
      "count": 2,
      "position": 810,
      "word": "yourself"
    },
    {
      "line": 70,
      "count": 4,
      "position": 494,
      "word": "up"
    },
    {
      "line": 148,
      "count": 1,
      "position": 1036,
      "word": "rapunzel"
    },
    {
      "line": 2,
      "count": 8,
      "position": 19,
      "word": "this"
    },
    {
      "line": 0,
      "count": 2,
      "position": 0,
      "word": "look"
    },
    {
      "line": 161,
      "count": 2,
      "position": 1129,
      "word": "lumma"
    },
    {
      "line": 119,
      "count": 2,
      "position": 839,
      "word": "once"
    },
    {
      "line": 59,
      "count": 1,
      "position": 413,
      "word": "youthful"
    },
    {
      "line": 7,
      "count": 8,
      "position": 53,
      "word": "know"
    },
    {
      "line": 24,
      "count": 1,
      "position": 169,
      "word": "knot"
    },
    {
      "line": 110,
      "count": 1,
      "position": 774,
      "word": "woken"
    },
    {
      "line": 66,
      "count": 2,
      "position": 463,
      "word": "full"
    },
    {
      "line": 88,
      "count": 1,
      "position": 622,
      "word": "thumbs"
    },
    {
      "line": 145,
      "count": 1,
      "position": 1016,
      "word": "warp"
    },
    {
      "line": 44,
      "count": 1,
      "position": 308,
      "word": "drop"
    },
    {
      "line": 131,
      "count": 1,
      "position": 920,
      "word": "crunch"
    },
    {
      "line": 158,
      "count": 1,
      "position": 1111,
      "word": "next"
    },
    {
      "line": 15,
      "count": 6,
      "position": 109,
      "word": "nod"
    },
    {
      "line": 45,
      "count": 1,
      "position": 320,
      "word": "rough"
    },
    {
      "line": 141,
      "count": 1,
      "position": 989,
      "word": "away"
    },
    {
      "line": 133,
      "count": 1,
      "position": 931,
      "word": "color"
    },
    {
      "line": 205,
      "count": 1,
      "position": 1439,
      "word": "asking"
    },
    {
      "line": 54,
      "count": 1,
      "position": 379,
      "word": "show"
    },
    {
      "line": 78,
      "count": 1,
      "position": 550,
      "word": "fags"
    },
    {
      "line": 87,
      "count": 2,
      "position": 613,
      "word": "that's"
    },
    {
      "line": 207,
      "count": 1,
      "position": 1455,
      "word": "bitter"
    },
    {
      "line": 114,
      "count": 1,
      "position": 800,
      "word": "we"
    },
    {
      "line": 160,
      "count": 1,
      "position": 1124,
      "word": "speed"
    },
    {
      "line": 165,
      "count": 1,
      "position": 1157,
      "word": "anything"
    },
    {
      "line": 1,
      "count": 6,
      "position": 8,
      "word": "not"
    },
    {
      "line": 114,
      "count": 1,
      "position": 804,
      "word": "common"
    },
    {
      "line": 35,
      "count": 1,
      "position": 247,
      "word": "yackety-yack"
    },
    {
      "line": 16,
      "count": 4,
      "position": 112,
      "word": "now"
    },
    {
      "line": 23,
      "count": 1,
      "position": 164,
      "word": "half-cock"
    },
    {
      "line": 36,
      "count": 1,
      "position": 257,
      "word": "lyrical"
    },
    {
      "line": 175,
      "count": 1,
      "position": 1230,
      "word": "he's"
    },
    {
      "line": 90,
      "count": 1,
      "position": 636,
      "word": "every"
    },
    {
      "line": 82,
      "count": 3,
      "position": 577,
      "word": "gay"
    },
    {
      "line": 115,
      "count": 1,
      "position": 809,
      "word": "pinch"
    },
    {
      "line": 148,
      "count": 2,
      "position": 1042,
      "word": "normal"
    },
    {
      "line": 117,
      "count": 1,
      "position": 822,
      "word": "brutal"
    },
    {
      "line": 205,
      "count": 1,
      "position": 1438,
      "word": "they're"
    },
    {
      "line": 154,
      "count": 1,
      "position": 1079,
      "word": "mayweather's"
    },
    {
      "line": 198,
      "count": 1,
      "position": 1388,
      "word": "tongue-and-cheek"
    },
    {
      "line": 0,
      "count": 8,
      "position": 2,
      "word": "was"
    },
    {
      "line": 72,
      "count": 1,
      "position": 504,
      "word": "run-dmc"
    },
    {
      "line": 212,
      "count": 1,
      "position": 1484,
      "word": "lemonade"
    },
    {
      "line": 37,
      "count": 4,
      "position": 264,
      "word": "i'll"
    },
    {
      "line": 90,
      "count": 4,
      "position": 630,
      "word": "way"
    },
    {
      "line": 7,
      "count": 12,
      "position": 54,
      "word": "what"
    },
    {
      "line": 46,
      "count": 1,
      "position": 325,
      "word": "maxi-pad"
    },
    {
      "line": 131,
      "count": 1,
      "position": 917,
      "word": "grind"
    },
    {
      "line": 161,
      "count": 1,
      "position": 1133,
      "word": "assuming"
    },
    {
      "line": 202,
      "count": 1,
      "position": 1414,
      "word": "funky"
    },
    {
      "line": 36,
      "count": 4,
      "position": 253,
      "word": "time"
    },
    {
      "line": 171,
      "count": 1,
      "position": 1197,
      "word": "forever"
    },
    {
      "line": 186,
      "count": 2,
      "position": 1306,
      "word": "verses"
    },
    {
      "line": 155,
      "count": 1,
      "position": 1087,
      "word": "play"
    },
    {
      "line": 79,
      "count": 1,
      "position": 556,
      "word": "'til"
    },
    {
      "line": 192,
      "count": 1,
      "position": 1350,
      "word": "brung"
    },
    {
      "line": 153,
      "count": 2,
      "position": 1071,
      "word": "fab"
    },
    {
      "line": 151,
      "count": 1,
      "position": 1062,
      "word": "ya"
    },
    {
      "line": 160,
      "count": 1,
      "position": 1126,
      "word": "fad"
    },
    {
      "line": 113,
      "count": 1,
      "position": 792,
      "word": "mom"
    },
    {
      "line": 23,
      "count": 9,
      "position": 162,
      "word": "when"
    },
    {
      "line": 30,
      "count": 2,
      "position": 211,
      "word": "hell"
    },
    {
      "line": 153,
      "count": 1,
      "position": 1077,
      "word": "fag"
    },
    {
      "line": 138,
      "count": 2,
      "position": 971,
      "word": "put"
    },
    {
      "line": 30,
      "count": 4,
      "position": 215,
      "word": "'em"
    },
    {
      "line": 116,
      "count": 1,
      "position": 817,
      "word": "pupil"
    },
    {
      "line": 204,
      "count": 1,
      "position": 1430,
      "word": "devils"
    },
    {
      "line": 155,
      "count": 1,
      "position": 1088,
      "word": "piano"
    },
    {
      "line": 200,
      "count": 1,
      "position": 1405,
      "word": "bumping"
    },
    {
      "line": 175,
      "count": 1,
      "position": 1227,
      "word": "elevator"
    },
    {
      "line": 208,
      "count": 1,
      "position": 1456,
      "word": "hatred"
    },
    {
      "line": 218,
      "count": 2,
      "position": 1532,
      "word": "her"
    },
    {
      "line": 144,
      "count": 1,
      "position": 1012,
      "word": "stuck"
    },
    {
      "line": 24,
      "count": 1,
      "position": 168,
      "word": "fat"
    },
    {
      "line": 44,
      "count": 1,
      "position": 313,
      "word": "wrath"
    },
    {
      "line": 218,
      "count": 1,
      "position": 1529,
      "word": "broad"
    },
    {
      "line": 203,
      "count": 1,
      "position": 1426,
      "word": "struggling"
    },
    {
      "line": 200,
      "count": 1,
      "position": 1400,
      "word": "asleep"
    },
    {
      "line": 95,
      "count": 1,
      "position": 665,
      "word": "nobody"
    },
    {
      "line": 68,
      "count": 3,
      "position": 478,
      "word": "hey"
    },
    {
      "line": 125,
      "count": 1,
      "position": 879,
      "word": "case"
    },
    {
      "line": 166,
      "count": 1,
      "position": 1167,
      "word": "it'll"
    },
    {
      "line": 168,
      "count": 1,
      "position": 1180,
      "word": "give"
    },
    {
      "line": 26,
      "count": 7,
      "position": 187,
      "word": "still"
    },
    {
      "line": 45,
      "count": 1,
      "position": 318,
      "word": "having"
    },
    {
      "line": 212,
      "count": 1,
      "position": 1490,
      "word": "batter"
    },
    {
      "line": 67,
      "count": 1,
      "position": 473,
      "word": "lakim"
    },
    {
      "line": 196,
      "count": 1,
      "position": 1376,
      "word": "leagues"
    },
    {
      "line": 94,
      "count": 1,
      "position": 658,
      "word": "work"
    },
    {
      "line": 181,
      "count": 2,
      "position": 1268,
      "word": "lose"
    },
    {
      "line": 134,
      "count": 2,
      "position": 941,
      "word": "come"
    },
    {
      "line": 172,
      "count": 1,
      "position": 1209,
      "word": "they'll"
    },
    {
      "line": 164,
      "count": 1,
      "position": 1149,
      "word": "innovative"
    },
    {
      "line": 62,
      "count": 1,
      "position": 435,
      "word": "moon"
    },
    {
      "line": 114,
      "count": 1,
      "position": 798,
      "word": "ramen"
    },
    {
      "line": 118,
      "count": 1,
      "position": 830,
      "word": "utilize"
    },
    {
      "line": 35,
      "count": 1,
      "position": 251,
      "word": "exact"
    },
    {
      "line": 67,
      "count": 1,
      "position": 475,
      "word": "2pac"
    },
    {
      "line": 191,
      "count": 1,
      "position": 1342,
      "word": "junky"
    },
    {
      "line": 80,
      "count": 1,
      "position": 560,
      "word": "flock"
    },
    {
      "line": 102,
      "count": 1,
      "position": 717,
      "word": "racing"
    },
    {
      "line": 209,
      "count": 1,
      "position": 1468,
      "word": "sympathetic"
    },
    {
      "line": 74,
      "count": 2,
      "position": 523,
      "word": "church"
    },
    {
      "line": 118,
      "count": 1,
      "position": 826,
      "word": "futile"
    },
    {
      "line": 62,
      "count": 1,
      "position": 437,
      "word": "ppeeyoom"
    },
    {
      "line": 56,
      "count": 1,
      "position": 396,
      "word": "secret"
    },
    {
      "line": 2,
      "count": 29,
      "position": 14,
      "word": "i'm"
    },
    {
      "line": 64,
      "count": 1,
      "position": 452,
      "word": "vehicle"
    },
    {
      "line": 95,
      "count": 2,
      "position": 669,
      "word": "out"
    },
    {
      "line": 217,
      "count": 1,
      "position": 1521,
      "word": "overseas"
    },
    {
      "line": 73,
      "count": 2,
      "position": 511,
      "word": "rock"
    },
    {
      "line": 179,
      "count": 1,
      "position": 1258,
      "word": "fuse"
    },
    {
      "line": 20,
      "count": 1,
      "position": 144,
      "word": "computer"
    },
    {
      "line": 177,
      "count": 1,
      "position": 1243,
      "word": "confuse"
    },
    {
      "line": 219,
      "count": 1,
      "position": 1533,
      "word": "fall"
    },
    {
      "line": 203,
      "count": 1,
      "position": 1427,
      "word": "angels"
    },
    {
      "line": 2,
      "count": 11,
      "position": 18,
      "word": "get"
    },
    {
      "line": 86,
      "count": 1,
      "position": 605,
      "word": "place"
    },
    {
      "line": 8,
      "count": 2,
      "position": 57,
      "word": "means"
    },
    {
      "line": 107,
      "count": 1,
      "position": 749,
      "word": "thor"
    },
    {
      "line": 103,
      "count": 1,
      "position": 726,
      "word": "earnhardt"
    },
    {
      "line": 167,
      "count": 2,
      "position": 1174,
      "word": "more"
    },
    {
      "line": 117,
      "count": 1,
      "position": 821,
      "word": "honesty's"
    },
    {
      "line": 211,
      "count": 1,
      "position": 1479,
      "word": "life's"
    },
    {
      "line": 30,
      "count": 2,
      "position": 214,
      "word": "kill"
    },
    {
      "line": 86,
      "count": 1,
      "position": 602,
      "word": "gathering"
    },
    {
      "line": 65,
      "count": 1,
      "position": 459,
      "word": "lead"
    },
    {
      "line": 190,
      "count": 1,
      "position": 1330,
      "word": "nice"
    },
    {
      "line": 3,
      "count": 1,
      "position": 27,
      "word": "wrong"
    },
    {
      "line": 36,
      "count": 1,
      "position": 258,
      "word": "acrobat"
    },
    {
      "line": 123,
      "count": 1,
      "position": 863,
      "word": "help"
    },
    {
      "line": 183,
      "count": 2,
      "position": 1281,
      "word": "songs"
    },
    {
      "line": 58,
      "count": 1,
      "position": 411,
      "word": "rage"
    },
    {
      "line": 83,
      "count": 1,
      "position": 584,
      "word": "barely"
    },
    {
      "line": 134,
      "count": 1,
      "position": 944,
      "word": "censor"
    },
    {
      "line": 136,
      "count": 1,
      "position": 957,
      "word": "mathers"
    },
    {
      "line": 47,
      "count": 1,
      "position": 335,
      "word": "masterfully"
    },
    {
      "line": 105,
      "count": 1,
      "position": 736,
      "word": "before"
    },
    {
      "line": 81,
      "count": 1,
      "position": 567,
      "word": "tell"
    },
    {
      "line": 44,
      "count": 2,
      "position": 310,
      "word": "bombs"
    },
    {
      "line": 75,
      "count": 2,
      "position": 530,
      "word": "flames"
    },
    {
      "line": 215,
      "count": 1,
      "position": 1507,
      "word": "him"
    },
    {
      "line": 178,
      "count": 1,
      "position": 1247,
      "word": "hip"
    },
    {
      "line": 60,
      "count": 1,
      "position": 422,
      "word": "hit"
    },
    {
      "line": 27,
      "count": 1,
      "position": 195,
      "word": "his"
    },
    {
      "line": 161,
      "count": 1,
      "position": 1128,
      "word": "summa"
    },
    {
      "line": 2,
      "count": 3,
      "position": 15,
      "word": "only"
    },
    {
      "line": 110,
      "count": 1,
      "position": 771,
      "word": "should"
    },
    {
      "line": 125,
      "count": 1,
      "position": 875,
      "word": "few"
    },
    {
      "line": 14,
      "count": 11,
      "position": 103,
      "word": "from"
    },
    {
      "line": 43,
      "count": 2,
      "position": 303,
      "word": "blow"
    },
    {
      "line": 70,
      "count": 4,
      "position": 492,
      "word": "day"
    },
    {
      "line": 106,
      "count": 1,
      "position": 747,
      "word": "you'll"
    },
    {
      "line": 6,
      "count": 16,
      "position": 45,
      "word": "like"
    },
    {
      "line": 129,
      "count": 3,
      "position": 903,
      "word": "king"
    },
    {
      "line": 3,
      "count": 4,
      "position": 23,
      "word": "minutes"
    },
    {
      "line": 46,
      "count": 11,
      "position": 326,
      "word": "it's"
    },
    {
      "line": 197,
      "count": 1,
      "position": 1379,
      "word": "ill"
    },
    {
      "line": 60,
      "count": 1,
      "position": 421,
      "word": "nuisance"
    },
    {
      "line": 190,
      "count": 1,
      "position": 1335,
      "word": "sacrifice"
    },
    {
      "line": 27,
      "count": 1,
      "position": 191,
      "word": "monica"
    },
    {
      "line": 87,
      "count": 1,
      "position": 609,
      "word": "vey"
    },
    {
      "line": 105,
      "count": 1,
      "position": 740,
      "word": "planet's"
    },
    {
      "line": 147,
      "count": 1,
      "position": 1031,
      "word": "rhyme"
    },
    {
      "line": 170,
      "count": 1,
      "position": 1190,
      "word": "fading"
    },
    {
      "line": 11,
      "count": 1,
      "position": 81,
      "word": "chances"
    },
    {
      "line": 106,
      "count": 2,
      "position": 743,
      "word": "asgard"
    },
    {
      "line": 124,
      "count": 1,
      "position": 873,
      "word": "keep"
    },
    {
      "line": 191,
      "count": 1,
      "position": 1340,
      "word": "flunky"
    },
    {
      "line": 73,
      "count": 3,
      "position": 516,
      "word": "fame"
    },
    {
      "line": 156,
      "count": 1,
      "position": 1095,
      "word": "24/7"
    },
    {
      "line": 16,
      "count": 2,
      "position": 113,
      "word": "who"
    },
    {
      "line": 134,
      "count": 1,
      "position": 939,
      "word": "here"
    },
    {
      "line": 55,
      "count": 2,
      "position": 390,
      "word": "everybody"
    },
    {
      "line": 79,
      "count": 1,
      "position": 555,
      "word": "game"
    },
    {
      "line": 135,
      "count": 2,
      "position": 949,
      "word": "line"
    },
    {
      "line": 16,
      "count": 2,
      "position": 115,
      "word": "their"
    },
    {
      "line": 221,
      "count": 1,
      "position": 1547,
      "word": "why"
    },
    {
      "line": 61,
      "count": 1,
      "position": 427,
      "word": "asteroid"
    },
    {
      "line": 105,
      "count": 1,
      "position": 738,
      "word": "zod"
    },
    {
      "line": 177,
      "count": 1,
      "position": 1241,
      "word": "jealous"
    },
    {
      "line": 4,
      "count": 5,
      "position": 29,
      "word": "can"
    },
    {
      "line": 105,
      "count": 1,
      "position": 737,
      "word": "general"
    },
    {
      "line": 95,
      "count": 1,
      "position": 668,
      "word": "git"
    },
    {
      "line": 111,
      "count": 1,
      "position": 777,
      "word": "walking"
    },
    {
      "line": 112,
      "count": 1,
      "position": 787,
      "word": "floating"
    },
    {
      "line": 209,
      "count": 1,
      "position": 1465,
      "word": "patient"
    },
    {
      "line": 158,
      "count": 1,
      "position": 1108,
      "word": "station"
    },
    {
      "line": 18,
      "count": 3,
      "position": 126,
      "word": "said"
    },
    {
      "line": 102,
      "count": 1,
      "position": 720,
      "word": "track"
    },
    {
      "line": 24,
      "count": 1,
      "position": 173,
      "word": "profit"
    },
    {
      "line": 104,
      "count": 1,
      "position": 730,
      "word": "park"
    },
    {
      "line": 32,
      "count": 1,
      "position": 230,
      "word": "match"
    },
    {
      "line": 10,
      "count": 7,
      "position": 76,
      "word": "say"
    },
    {
      "line": 17,
      "count": 4,
      "position": 119,
      "word": "enough"
    },
    {
      "line": 109,
      "count": 1,
      "position": 768,
      "word": "totin'"
    },
    {
      "line": 32,
      "count": 1,
      "position": 224,
      "word": "really"
    },
    {
      "line": 170,
      "count": 1,
      "position": 1195,
      "word": "haters"
    },
    {
      "line": 103,
      "count": 2,
      "position": 723,
      "word": "nascar"
    },
    {
      "line": 15,
      "count": 4,
      "position": 105,
      "word": "front"
    },
    {
      "line": 31,
      "count": 1,
      "position": 221,
      "word": "hip-hop"
    },
    {
      "line": 58,
      "count": 1,
      "position": 410,
      "word": "simply"
    }
  ],
  "lines": 209
}